xhs_mcp_demo1/__init__.py
xhs_mcp_demo1-0.1.0.dist-info/METADATA
xhs_mcp_demo1-0.1.0.dist-info/WHEEL
xhs_mcp_demo1-0.1.0.dist-info/entry_points.txt
xhs_mcp_demo1-0.1.0.dist-info/RECORD
